{
    "tld": "io",
    "cloudflare": {
        "date": "2025-06-23T13:34:58.570834",
        "registration": {
            "usd": "45.00",
            "eur": "39.08"
        },
        "renewal": {
            "usd": "45.00",
            "eur": "39.08"
        }
    },
    "internetbs": {
        "date": "2025-06-23T16:05:14.647275",
        "registration": {
            "usd": "59.50",
            "eur": "54.01",
            "cad": "80.59",
            "gbp": "47.83",
            "jpy": "8.008"
        },
        "renewal": {
            "usd": "62.85",
            "eur": "57.05",
            "cad": "85.09",
            "gbp": "50.55",
            "jpy": "8.456"
        },
        "transfer": {
            "usd": "61.00",
            "eur": "55.37",
            "cad": "82.62",
            "gbp": "49.04",
            "jpy": "8.210"
        },
        "restore": {
            "usd": "132.85",
            "eur": "120.59",
            "cad": "179.95",
            "gbp": "106.85",
            "jpy": "17.877"
        }
    },
    "scaleway": {
        "date": "2025-06-23T13:35:01.753002",
        "registration": {
            "eur": "90.01"
        },
        "renewal": {
            "eur": "83.09"
        },
        "transfer": {
            "eur": "90.01"
        },
        "restore": {
            "eur": "116.00"
        }
    },
    "namecheap": {
        "date": "2025-06-23T16:05:18.626945",
        "registration": {
            "usd": "57.98",
            "eur": "50.35",
            "gbp": "42.99",
            "cad": "79.52"
        },
        "renewal": {
            "usd": "62.98",
            "eur": "54.69",
            "gbp": "46.69",
            "cad": "86.38"
        },
        "transfer": {
            "usd": "57.98",
            "eur": "50.35",
            "gbp": "42.99",
            "cad": "79.52"
        }
    },
    "gandi": {
        "date": "2025-06-23T16:04:53.699417",
        "registration": {
            "eur": "33.99",
            "usd": "37.99",
            "gbp": "28.99"
        },
        "renewal": {
            "eur": "59.99",
            "usd": "69.99",
            "gbp": "44.99"
        },
        "transfer": {
            "eur": "44.00",
            "usd": "49.00",
            "gbp": "36.75"
        },
        "owner_change": {
            "usd": "0.00",
            "gbp": "0.00",
            "eur": "0.00"
        },
        "restore": {
            "eur": "110.00",
            "usd": "120.00",
            "gbp": "90.00"
        }
    },
    "ovh": {
        "date": "2025-06-23T16:05:21.009311",
        "registration": {
            "currency": "usd",
            "price": "42.57",
            "eur": "40.89",
            "usd": "42.57",
            "cad": "60.90"
        },
        "renewal": {
            "currency": "usd",
            "price": "62.69",
            "eur": "59.79",
            "usd": "62.69",
            "cad": "80.69"
        },
        "transfer": {
            "currency": "usd",
            "price": "50.69",
            "eur": "48.29",
            "usd": "50.69",
            "cad": "65.29"
        }
    }
}