{
    "tld": "lawyer",
    "cloudflare": {
        "date": "2025-06-23T13:34:58.586981",
        "registration": {
            "usd": "43.18",
            "eur": "37.50"
        },
        "renewal": {
            "usd": "43.18",
            "eur": "37.50"
        }
    },
    "internetbs": {
        "date": "2025-06-23T16:05:14.687985",
        "registration": {
            "usd": "54.46",
            "eur": "49.43",
            "cad": "73.77",
            "gbp": "43.78",
            "jpy": "7.330"
        },
        "renewal": {
            "usd": "60.55",
            "eur": "54.95",
            "cad": "81.95",
            "gbp": "48.65",
            "jpy": "8.143"
        },
        "transfer": {
            "usd": "54.46",
            "eur": "49.43",
            "cad": "73.77",
            "gbp": "43.78",
            "jpy": "7.330"
        },
        "restore": {
            "usd": "180.75",
            "eur": "164.05",
            "cad": "244.75",
            "gbp": "145.29",
            "jpy": "24.318"
        }
    },
    "namecheap": {
        "date": "2025-06-23T16:05:18.641583",
        "registration": {
            "usd": "54.98",
            "eur": "47.75",
            "gbp": "40.76",
            "cad": "75.41"
        },
        "renewal": {
            "usd": "56.98",
            "eur": "49.48",
            "gbp": "42.24",
            "cad": "78.15"
        },
        "transfer": {
            "usd": "54.98",
            "eur": "47.75",
            "gbp": "40.76",
            "cad": "75.41"
        }
    },
    "gandi": {
        "date": "2025-06-23T16:05:04.965420",
        "registration": {
            "eur": "66.41",
            "usd": "76.38",
            "gbp": "57.11"
        },
        "renewal": {
            "eur": "140.00",
            "usd": "159.98",
            "gbp": "103.98"
        },
        "transfer": {
            "eur": "56.28",
            "usd": "64.71",
            "gbp": "48.40"
        },
        "owner_change": {
            "usd": "0.00",
            "gbp": "0.00",
            "eur": "0.00"
        },
        "restore": {
            "eur": "117.43",
            "usd": "135.05",
            "gbp": "100.98"
        }
    },
    "ovh": {
        "date": "2025-06-23T16:05:22.916455",
        "registration": {
            "currency": "usd",
            "price": "54.39",
            "eur": "49.89",
            "usd": "54.39",
            "cad": "72.79",
            "gbp": "42.89"
        },
        "renewal": {
            "currency": "usd",
            "price": "61.49",
            "eur": "56.39",
            "usd": "61.49",
            "cad": "82.29",
            "gbp": "48.49"
        },
        "transfer": {
            "currency": "usd",
            "price": "60.39",
            "eur": "55.39",
            "usd": "60.39",
            "cad": "80.89",
            "gbp": "47.59"
        }
    }
}