{
    "tld": "tg",
    "gandi": {
        "date": "2025-06-23T16:04:52.944357",
        "registration": {
            "eur": "110.00",
            "gbp": "94.60",
            "usd": "126.50"
        },
        "renewal": {
            "eur": "220.00",
            "gbp": "159.98",
            "usd": "247.98"
        },
        "transfer": {
            "eur": "94.05",
            "gbp": "80.88",
            "usd": "108.16"
        },
        "owner_change": {
            "eur": "110.00",
            "gbp": "94.60",
            "usd": "126.50"
        }
    }
}