{
    "tld": "clic",
    "namecheap": {
        "date": "2025-06-23T16:05:18.528123",
        "registration": {
            "usd": "16.98",
            "eur": "14.75",
            "gbp": "12.59",
            "cad": "23.29"
        },
        "renewal": {
            "usd": "16.98",
            "eur": "14.75",
            "gbp": "12.59",
            "cad": "23.29"
        },
        "transfer": {
            "usd": "16.98",
            "eur": "14.75",
            "gbp": "12.59",
            "cad": "23.29"
        }
    }
}