{
    "tld": "cx",
    "internetbs": {
        "date": "2025-06-23T16:05:14.644099",
        "registration": {
            "usd": "18.99",
            "eur": "16.99",
            "cad": "25.99",
            "gbp": "14.99",
            "jpy": "2.544"
        },
        "renewal": {
            "usd": "21.65",
            "eur": "19.59",
            "cad": "28.85",
            "gbp": "17.49",
            "jpy": "2.869"
        },
        "transfer": {
            "usd": "20.99",
            "eur": "18.99",
            "cad": "27.99",
            "gbp": "16.99",
            "jpy": "2.786"
        },
        "restore": {
            "usd": "88.69",
            "eur": "89.85",
            "cad": "118.75",
            "gbp": "76.05",
            "jpy": "12.420"
        }
    },
    "namecheap": {
        "date": "2025-06-23T16:05:18.549275",
        "registration": {
            "usd": "19.98",
            "eur": "17.35",
            "gbp": "14.81",
            "cad": "27.40"
        },
        "renewal": {
            "usd": "19.98",
            "eur": "17.35",
            "gbp": "14.81",
            "cad": "27.40"
        },
        "transfer": {
            "usd": "19.98",
            "eur": "17.35",
            "gbp": "14.81",
            "cad": "27.40"
        }
    },
    "gandi": {
        "date": "2025-06-23T16:04:56.148340",
        "registration": {
            "eur": "66.00",
            "gbp": "64.00",
            "usd": "75.00"
        },
        "renewal": {
            "eur": "100.00",
            "gbp": "79.98",
            "usd": "111.98"
        },
        "transfer": {
            "eur": "56.50",
            "gbp": "47.50",
            "usd": "73.50"
        },
        "owner_change": {
            "usd": "0.00",
            "gbp": "0.00",
            "eur": "0.00"
        },
        "restore": {
            "eur": "105.00",
            "gbp": "81.00",
            "usd": "135.00"
        }
    },
    "ovh": {
        "date": "2025-06-23T16:05:22.863197",
        "registration": {
            "currency": "usd",
            "price": "94.99",
            "eur": "86.99",
            "usd": "94.99",
            "cad": "131.99",
            "gbp": "73.94"
        },
        "renewal": {
            "currency": "usd",
            "price": "68.99",
            "eur": "62.99",
            "usd": "68.99",
            "cad": "95.99",
            "gbp": "62.99"
        },
        "transfer": {
            "currency": "usd",
            "price": "69.29",
            "eur": "62.39",
            "usd": "69.29",
            "cad": "92.99",
            "gbp": "57.99"
        }
    }
}