{
    "tld": "nxs",
    "namecheap": {
        "date": "2025-06-23T16:05:18.674803",
        "registration": {
            "usd": "37.98",
            "eur": "32.98",
            "gbp": "28.16",
            "cad": "52.09"
        },
        "renewal": {
            "usd": "7.98",
            "eur": "6.93",
            "gbp": "5.92",
            "cad": "10.94"
        },
        "transfer": {
            "usd": "7.98",
            "eur": "6.93",
            "gbp": "5.92",
            "cad": "10.94"
        }
    }
}