{
    "tld": "sexy",
    "internetbs": {
        "date": "2025-06-23T16:05:14.776514",
        "registration": {
            "usd": "2.800",
            "eur": "2.541",
            "cad": "3.792",
            "gbp": "2.251",
            "jpy": "376.881"
        },
        "renewal": {
            "usd": "2.884",
            "eur": "2.617",
            "cad": "3.906",
            "gbp": "2.318",
            "jpy": "388.187"
        },
        "transfer": {
            "usd": "2.800",
            "eur": "2.541",
            "cad": "3.792",
            "gbp": "2.251",
            "jpy": "376.881"
        },
        "restore": {
            "usd": "3.027",
            "eur": "2.747",
            "cad": "4.100",
            "gbp": "2.433",
            "jpy": "407.433"
        }
    },
    "scaleway": {
        "date": "2025-06-23T13:35:01.779006",
        "registration": {
            "eur": "32.73"
        },
        "renewal": {
            "eur": "30.22"
        },
        "transfer": {
            "eur": "32.73"
        },
        "restore": {
            "eur": "80.01"
        }
    },
    "namecheap": {
        "date": "2025-06-23T16:05:18.722239",
        "registration": {
            "usd": "2.998",
            "eur": "2.603",
            "gbp": "2.222",
            "cad": "4.111"
        },
        "renewal": {
            "usd": "3.098",
            "eur": "2.690",
            "gbp": "2.296",
            "cad": "4.248"
        },
        "transfer": {
            "usd": "2.898",
            "eur": "2.516",
            "gbp": "2.148",
            "cad": "3.974"
        }
    },
    "gandi": {
        "date": "2025-06-23T16:05:03.340235",
        "registration": {
            "eur": "2.500",
            "usd": "2.750",
            "gbp": "2.150"
        },
        "renewal": {
            "eur": "4.090",
            "usd": "4.623",
            "gbp": "3.447"
        },
        "transfer": {
            "eur": "2.500",
            "usd": "2.750",
            "gbp": "2.150"
        },
        "owner_change": {
            "usd": "0.00",
            "gbp": "0.00",
            "eur": "0.00"
        },
        "restore": {
            "eur": "4.380",
            "usd": "4.818",
            "gbp": "3.766"
        }
    },
    "ovh": {
        "date": "2025-06-23T16:05:22.987264",
        "registration": {
            "currency": "usd",
            "price": "31.99",
            "eur": "28.99",
            "usd": "31.99",
            "cad": "43.99",
            "gbp": "24.64"
        },
        "renewal": {
            "currency": "usd",
            "price": "34.99",
            "eur": "31.99",
            "usd": "34.99",
            "cad": "48.99",
            "gbp": "27.19"
        },
        "transfer": {
            "currency": "usd",
            "price": "35.69",
            "eur": "32.19",
            "usd": "35.69",
            "cad": "47.89",
            "gbp": "28.59"
        }
    }
}