{
    "tld": "si",
    "internetbs": {
        "date": "2025-06-23T13:35:01.333418",
        "registration": {
            "usd": "21.99",
            "eur": "19.99"
        },
        "renewal": {
            "usd": "24.75",
            "eur": "22.65"
        },
        "transfer": "",
        "restore": {
            "usd": "79.89",
            "eur": "80.89"
        }
    },
    "gandi": {
        "date": "2025-06-23T14:52:17.160859",
        "registration": {
            "eur": "90.00"
        },
        "renewal": {
            "usd": "0.00",
            "eur": "180.00"
        },
        "transfer": {
            "eur": "180.00",
            "usd": "0.00"
        }
    },
    "ovh": {
        "date": "2025-06-23T14:33:24.341123",
        "registration": {
            "currency": "usd",
            "price": "11.49",
            "eur": "9.99",
            "usd": "11.49"
        },
        "renewal": {
            "currency": "usd",
            "price": "15.89",
            "eur": "14.29",
            "usd": "15.89"
        },
        "transfer": {
            "currency": "usd",
            "price": "0",
            "eur": "0",
            "usd": "0"
        }
    }
}