{
    "tld": "gh",
    "gandi": {
        "date": "2025-06-23T16:04:58.394301",
        "registration": {
            "eur": "165.00",
            "usd": "189.75",
            "gbp": "141.90"
        },
        "renewal": {
            "eur": "370.00",
            "usd": "415.98",
            "gbp": "263.98"
        },
        "transfer": {
            "eur": "190.00",
            "usd": "218.50",
            "gbp": "163.40"
        },
        "owner_change": {
            "eur": "110.00",
            "usd": "126.50",
            "gbp": "94.60"
        }
    }
}