{
    "tld": "co.in",
    "internetbs": {
        "date": "2025-06-23T00:51:55.529656",
        "registration": {
            "usd": "9.99",
            "eur": "9.99"
        },
        "renewal": {
            "usd": "11.35",
            "eur": "10.29"
        },
        "transfer": {
            "usd": "10.99",
            "eur": "9.99"
        },
        "restore": {
            "usd": "72.39",
            "eur": "73.35"
        }
    },
    "namecheap": {
        "date": "2025-06-23T00:51:58.446548",
        "registration": {
            "usd": "5.98",
            "eur": "5.19"
        },
        "renewal": {
            "usd": "6.98",
            "eur": "6.06"
        },
        "transfer": {
            "usd": "5.98",
            "eur": "5.19"
        }
    },
    "ovh": {
        "date": "2025-06-23T00:52:05.041491",
        "registration": {
            "eur": "8.99",
            "usd": "10.49"
        },
        "renewal": {
            "eur": "6.99",
            "usd": "7.99"
        },
        "transfer": {
            "eur": "6.99",
            "usd": "7.99"
        }
    }
}