{
    "tld": "viajes",
    "cloudflare": {
        "date": "2025-06-23T00:51:51.603979",
        "registration": {
            "usd": "35.18",
            "eur": "30.55"
        },
        "renewal": {
            "usd": "35.18",
            "eur": "30.55"
        }
    },
    "internetbs": {
        "date": "2025-06-23T00:51:55.684324",
        "registration": {
            "usd": "48.99",
            "eur": "44.99"
        },
        "renewal": {
            "usd": "55.55",
            "eur": "50.49"
        },
        "transfer": {
            "usd": "53.90",
            "eur": "48.99"
        },
        "restore": {
            "usd": "98.65",
            "eur": "99.89"
        }
    },
    "scaleway": {
        "date": "2025-06-23T00:51:55.987611",
        "registration": {
            "eur": "45.73"
        },
        "renewal": {
            "eur": "48.22"
        },
        "transfer": {
            "eur": "45.73"
        },
        "restore": {
            "eur": "51.01"
        }
    },
    "namecheap": {
        "date": "2025-06-23T00:51:58.660499",
        "registration": {
            "usd": "43.98",
            "eur": "38.19"
        },
        "renewal": {
            "usd": "45.98",
            "eur": "39.93"
        },
        "transfer": {
            "usd": "43.98",
            "eur": "38.19"
        }
    },
    "gandi": {
        "date": "2025-06-23T00:52:02.772702",
        "registration": {
            "eur": "58.15"
        },
        "renewal": {
            "eur": "49.28"
        },
        "transfer": {
            "eur": "111.98"
        },
        "owner_change": {
            "usd": "0.00"
        },
        "restore": {
            "eur": "110.41"
        }
    },
    "ovh": {
        "date": "2025-06-23T00:52:05.210821",
        "registration": {
            "eur": "41.39",
            "usd": "45.89"
        },
        "renewal": {
            "eur": "44.59",
            "usd": "49.39"
        },
        "transfer": {
            "eur": "41.99",
            "usd": "46.59"
        }
    }
}