{
    "tld": "voting",
    "namecheap": {
        "date": "2025-06-23T00:44:56.713569",
        "registration": {
            "usd": "1.398",
            "eur": "1.214"
        },
        "renewal": {
            "usd": "1.398",
            "eur": "1.214"
        }
    },
    "gandi": {
        "date": "2025-06-23T00:45:00.611027",
        "registration": {
            "eur": "726.40"
        },
        "renewal": {
            "eur": "717.40"
        },
        "transfer": {
            "eur": "1.271"
        },
        "owner_change": {
            "": "0.00"
        },
        "restore": {
            "eur": "811.40"
        }
    }
}