{
    "tld": "在线",
    "namecheap": {
        "date": "2025-06-23T00:44:56.723730",
        "renewal": {
            "usd": "35.98",
            "eur": "31.25"
        }
    },
    "gandi": {
        "date": "2025-06-23T00:44:56.965406",
        "registration": {
            "eur": "217.15"
        },
        "renewal": {
            "eur": "208.15"
        },
        "transfer": {
            "eur": "423.98"
        },
        "owner_change": {
            "": "0.00"
        },
        "restore": {
            "eur": "303.15"
        }
    }
}