{
    "tld": "feeling",
    "namecheap": {
        "date": "2025-06-23T16:05:18.582844",
        "registration": {
            "usd": "120.98",
            "eur": "105.06",
            "gbp": "89.69",
            "cad": "165.93"
        },
        "renewal": {
            "usd": "120.98",
            "eur": "105.06",
            "gbp": "89.69",
            "cad": "165.93"
        },
        "transfer": {
            "usd": "120.98",
            "eur": "105.06",
            "gbp": "89.69",
            "cad": "165.93"
        }
    }
}